{
  "dataset_revision": "65b79d1d13f80053f67aca9498d9402c2d9f1f40",
  "evaluation_time": 185.7580370903015,
  "kg_co2_emissions": null,
  "mteb_version": "1.14.12",
  "scores": {
    "test": [
      {
        "hf_subset": "default",
        "languages": [
          "eng-Latn"
        ],
        "main_score": 0.38472599707993654,
        "v_measure": 0.38472599707993654,
        "v_measure_std": 0.00996070438521638,
        "v_measures": [
          0.40580294705299275,
          0.3873287247047351,
          0.3784002050746416,
          0.3797685879867683,
          0.38484759654876244,
          0.3874122387592651,
          0.36468448259138964,
          0.38865112609376,
          0.3800909995455402,
          0.3902730624415101
        ]
      }
    ]
  },
  "task_name": "BiorxivClusteringP2P"
}